algpro/__init__.py
algpro/algpro.py
algpros/__init__.py
algpros/algpros.py
algpros-0.0.2.dist-info/LICENSE
algpros-0.0.2.dist-info/METADATA
algpros-0.0.2.dist-info/WHEEL
algpros-0.0.2.dist-info/top_level.txt
algpros-0.0.2.dist-info/RECORD
